drt_telea/__init__.py
drt_telea/telea.py
drt_telea-0.0.5.dist-info/LICENSE
drt_telea-0.0.5.dist-info/METADATA
drt_telea-0.0.5.dist-info/WHEEL
drt_telea-0.0.5.dist-info/top_level.txt
drt_telea-0.0.5.dist-info/RECORD
