Metadata-Version: 2.1
Name: drt-telea
Version: 0.0.5
Summary: Python implementation of Telea inpaiting method
Home-page: https://github.com/dimiaa/drt-telea
Author: Dmitry Trokhachev
Author-email: dimiaa573@gmail.com
Project-URL: Bug Tracker, https://github.com/dimiaa/drt-telea/issues
Classifier: Programming Language :: Python :: 3
Classifier: License :: OSI Approved :: BSD License
Classifier: Operating System :: OS Independent
Requires-Python: >=3.6,<3.11
License-File: LICENSE
Requires-Dist: numpy
